{
  "id": "3a5a3949-927a-4eaf-ac82-e16a0b87d06a",
  "name": "Eggnog",
  "ingredients": [
    {"amount": "2", "unit": "oz", "item": "brandy"},
    {"amount": "1", "unit": "egg", "item": "egg"},
    {"amount": "0.75", "unit": "oz", "item": "demerara sugar"},
    {"amount": "1", "unit": "oz", "item": "heavy cream"}
  ],
  "instructions": [
    "Place all ingredients into a shaker.",
    "Dry shake for 20 seconds (no ice).",
    "Add ice and shake for an additional 10 seconds.",
    "Double strain into a chilled glass.",
    "Garnish with freshly grated nutmeg."
  ],
  "glass": "coupe",
  "tags": ["holiday", "rich", "sweet"],
  "spirit": "brandy",
  "created_at": "2025-12-21T04:25:35+00:00"
}
